{
  "workflow_info": {
    "timestamp": "2025-06-26T09:30:14.657501",
    "base_path": "../sample_dataset",
    "api_key_masked": "33170cfe-f...",
    "workflow_version": "1.0.0"
  },
  "upload_summary": {
    "available": true,
    "total_datasets": 5,
    "successful_uploads": 5,
    "failed_uploads": 0,
    "first_dataset_id": "10.34847/nkl.2fd109sy",
    "dataset_types": {}
  },
  "collections_summary": {
    "available": true,
    "total_collections": 3,
    "successful_collections": 3,
    "failed_collections": 0,
    "first_collection_id": "10.34847/nkl.2b83lr27"
  },
  "quality_summary": {
    "available": true,
    "analysis_timestamp": "Unknown",
    "total_items_analyzed": 0,
    "overall_quality_score": 0.0,
    "issues_found": 0,
    "recommendations_count": 4
  },
  "enhancement_summary": {
    "data_enhancements": {
      "available": true,
      "total_modifications": 10,
      "unique_datasets": 5,
      "action_types": {
        "add_metadata": 10
      }
    },
    "collection_enhancements": {
      "available": true,
      "total_modifications": 3,
      "unique_collections": 3,
      "action_types": {
        "modify": 3
      }
    }
  },
  "overall_statistics": {
    "total_operations": 8,
    "successful_operations": 5,
    "total_items_created": 8,
    "total_enhancements_applied": 13,
    "workflow_success_rate": 62.5
  },
  "execution_timeline": [
    {
      "operation": "Upload",
      "timestamp": "2025-06-25T23:08:45.961076",
      "file": "upload_results.csv"
    },
    {
      "operation": "Collections",
      "timestamp": "2025-06-25T23:08:47.275804",
      "file": "collections_output.csv"
    },
    {
      "operation": "Collection Enhancements",
      "timestamp": "2025-06-25T23:14:08.382809",
      "file": "auto_collection_modifications.csv"
    },
    {
      "operation": "Data Enhancements",
      "timestamp": "2025-06-26T09:27:21.674078",
      "file": "auto_data_modifications.csv"
    },
    {
      "operation": "Quality Analysis",
      "timestamp": "2025-06-26T09:28:06.055774",
      "file": "quality_report.json"
    }
  ],
  "success": true
}